scales.py
scales.py-0.1.4.dist-info/LICENSE
scales.py-0.1.4.dist-info/METADATA
scales.py-0.1.4.dist-info/WHEEL
scales.py-0.1.4.dist-info/top_level.txt
scales.py-0.1.4.dist-info/RECORD
