Metadata-Version: 2.1
Name: scales.py
Version: 0.1.4
Summary: A tool to generate stringed instrument visual aids
Home-page: https://github.com/zedchance/scales
Author: Zed Chance
Author-email: zedchance@gmail.com
License: MIT
Keywords: music guitar matplotlib
Platform: UNKNOWN
Classifier: Development Status :: 3 - Alpha
Classifier: Intended Audience :: Developers
Classifier: Topic :: Software Development :: Build Tools
Classifier: License :: OSI Approved :: MIT License
Classifier: Programming Language :: Python :: 3.7
Classifier: Programming Language :: Python :: 3.8
Requires-Python: >=3.7
Requires-Dist: matplotlib
Requires-Dist: numpy
